LICENSE
MANIFEST.in
README.rst
kirui_dev
setup.py
browser/__init__.py
browser/document.py
browser/webcomponent.py
django_kirui/__init__.py
django_kirui/context_processors.py
django_kirui/http.py
django_kirui/widgets.py
django_kirui/components/__init__.py
django_kirui/components/apps.py
django_kirui/components/forms.py
django_kirui/static/django_kirui/brython.min.js
django_kirui/static/django_kirui/brython_stdlib.js
django_kirui/static/django_kirui/kirui.brython.js
django_kirui/static/django_kirui/kirui.css
django_kirui/static/django_kirui/kirui.react.css
django_kirui/static/django_kirui/kirui.react.js
django_kirui/static/django_kirui/tinymce/tinymce.min.js
django_kirui/static/django_kirui/tinymce/icons/default/icons.min.js
django_kirui/static/django_kirui/tinymce/models/dom/model.min.js
django_kirui/static/django_kirui/tinymce/plugins/lists/plugin.min.js
django_kirui/static/django_kirui/tinymce/plugins/table/plugin.min.js
django_kirui/static/django_kirui/tinymce/skins/content/default/content.min.css
django_kirui/static/django_kirui/tinymce/skins/ui/oxide/content.min.css
django_kirui/static/django_kirui/tinymce/skins/ui/oxide/skin.min.css
django_kirui/static/django_kirui/tinymce/skins/ui/oxide/skin.shadowdom.min.css
django_kirui/static/django_kirui/tinymce/themes/silver/theme.min.js
django_kirui/templates/__init__.py
django_kirui/templates/samon.py
django_kirui/utils/__init__.py
django_kirui/utils/paginator.py
django_static_bundler/__init__.py
django_static_bundler/apps.py
django_static_bundler/urls.py
django_static_bundler/views.py
django_static_bundler/templatetags/__init__.py
django_static_bundler/templatetags/bundled_static.py
kirui/__init__.py
kirui/apps.py
kirui.egg-info/PKG-INFO
kirui.egg-info/SOURCES.txt
kirui.egg-info/dependency_links.txt
kirui.egg-info/top_level.txt
kirui/static/bootstrap/font/OpenSans-Italic.ttf
kirui/static/bootstrap/font/OpenSans-Light.ttf
kirui/static/bootstrap/font/OpenSans-LightItalic.ttf
kirui/static/bootstrap/font/OpenSans-Regular.ttf
kirui/static/bootstrap/font/OpenSans-SemiBold.ttf
kirui/static/bootstrap/font/OpenSans-SemiBoldItalic.ttf
