Metadata-Version: 2.1
Name: kirui
Version: 0.6.0
Summary: UI framework with React / Preact and Django SSR backend
Home-page: https://kirui.lovasb.com/
Author: Bence Lovas
Author-email: me@lovasb.com
License: UNKNOWN
Project-URL: Documentation, https://kirui.lovasb.com/
Project-URL: Source, https://gitlab.com/lovasb/kirui
Project-URL: Tracker, https://gitlab.com/lovasb/kirui/-/issues
Platform: UNKNOWN
Classifier: Environment :: Web Environment
Classifier: Intended Audience :: Developers
Classifier: License :: OSI Approved :: MIT License
Classifier: Operating System :: OS Independent
Classifier: Programming Language :: Python
Classifier: Programming Language :: Python :: 3
Classifier: Programming Language :: Python :: 3 :: Only
Classifier: Topic :: Internet :: WWW/HTTP
Classifier: Topic :: Internet :: WWW/HTTP :: Dynamic Content
Classifier: Topic :: Software Development :: Libraries :: Python Modules
License-File: LICENSE
